whishow/NotoSansCJKsc-Regular.ttf
whishow/__init__.py
whishow/__main__.py
whishow/easyplayer.py
whishow/stream.py
whishow/utils.py
whishow/whishow.py
whishow-1.3.5.dist-info/LICENSE
whishow-1.3.5.dist-info/METADATA
whishow-1.3.5.dist-info/WHEEL
whishow-1.3.5.dist-info/top_level.txt
whishow-1.3.5.dist-info/RECORD
