Metadata-Version: 2.1
Name: whishow
Version: 1.3.5
Summary: an online player for video stream
Home-page: https://github.com/coolEphemeroptera/Whishow
Author: wei.wang
Author-email: coolephemeroptera@gmail.com
License: MIT
Classifier: License :: OSI Approved :: MIT License
Classifier: Programming Language :: Python
Classifier: Programming Language :: Python :: 3
Classifier: Programming Language :: Python :: 3.6
Classifier: Programming Language :: Python :: Implementation :: CPython
Classifier: Programming Language :: Python :: Implementation :: PyPy
Requires-Python: >=3.10.0
License-File: LICENSE
Requires-Dist: pyav
Requires-Dist: opencv-python
Requires-Dist: soxr
Requires-Dist: pillow
Requires-Dist: pyaudio
Requires-Dist: numpy
Requires-Dist: pyyaml
Requires-Dist: keyboard
